{
  "address": "0x1b1f9C78b887765c9266dbE988c5d0318c34E269",
  "lastGamePlayed": 0,
  "inventoryItemCount": 0,
  "equippedItemCount": 0,
  "marketTradeListedCount": 0,
  "marketTradeSoldCount": 0,
  "transferredOutCount": 0,
  "holdings": {},
  "points": 56,
  "username": "lukotnakuyukot",
  "guildId": 5,
  "joinedGuildAt": 1628248835625,
  "isGuildMembershipActive": true,
  "guildMembershipTokenId": 3259,
  "rewardHistory": [],
  "rewards": {
    "runes": {
      "tal": 0.98,
      "amn": 0,
      "dol": 0.04,
      "sol": 0,
      "tir": 0,
      "shael": 0,
      "nef": 0,
      "zod": 0,
      "thul": 0,
      "ith": 0,
      "ort": 0
    },
    "items": {}
  },
  "lifetimeRewards": {
    "runes": {
      "tal": 0.98,
      "amn": 0,
      "dol": 0.04,
      "sol": 0,
      "tir": 0,
      "shael": 0,
      "nef": 0,
      "zod": 0,
      "thul": 0,
      "ith": 0,
      "ort": 0
    },
    "items": {}
  },
  "craftedItemCount": 1,
  "transferredInCount": 0
}