{
  "address": "0xe96201eB304D2424306E636B15a771a083AcDc03",
  "inventoryItemCount": 0,
  "equippedItemCount": 0,
  "marketTradeListedCount": 0,
  "marketTradeSoldCount": 0,
  "transferredOutCount": 0,
  "holdings": {},
  "points": 0,
  "isGuildMembershipActive": false,
  "guildMembershipTokenId": null,
  "rewardHistory": [],
  "rewards": {
    "runes": {
      "dol": 0.67,
      "nef": 0.588,
      "ort": 0.59,
      "tal": 0.53,
      "ith": 0.8160000000000001,
      "thul": 0.63,
      "zod": 1.5959999999999999,
      "amn": 0.906,
      "tir": 1.12,
      "shael": 1.01,
      "sol": 1.06
    },
    "items": {}
  },
  "lifetimeRewards": {
    "runes": {
      "amn": 0.906,
      "zod": 1.5959999999999999,
      "nef": 0.588,
      "ith": 0.8160000000000001,
      "dol": 0.67,
      "ort": 0.59,
      "tal": 0.53,
      "thul": 0.63,
      "tir": 1.12,
      "shael": 1.01,
      "sol": 1.06
    },
    "items": {}
  },
  "craftedItemCount": 0,
  "transferredInCount": 0
}