{
  "address": "0x89D8A8CA9c2d8Ae11c65EDd700dd54a8a70815C0",
  "lastGamePlayed": 0,
  "inventoryItemCount": 0,
  "equippedItemCount": 0,
  "marketTradeListedCount": 0,
  "marketTradeSoldCount": 0,
  "transferredOutCount": 0,
  "holdings": {},
  "points": 55,
  "username": "Shuuni",
  "guildId": 5,
  "joinedGuildAt": 1631114274171,
  "isGuildMembershipActive": true,
  "guildMembershipTokenId": 12210,
  "rewardHistory": [],
  "rewards": {
    "runes": {
      "ort": 0.9,
      "sol": 0.66,
      "zod": 1.543,
      "tir": 0.55,
      "nef": 0.9099999999999999,
      "dol": 0.76,
      "shael": 0.41,
      "ith": 0.9400000000000001,
      "amn": 0.78,
      "thul": 0.49,
      "tal": 0.78,
      "ral": 0.11,
      "hel": 0.11
    },
    "items": {}
  },
  "lifetimeRewards": {
    "runes": {
      "ith": 0.9400000000000001,
      "dol": 0.76,
      "ort": 0.9,
      "sol": 0.66,
      "zod": 1.543,
      "tir": 0.55,
      "nef": 0.9099999999999999,
      "shael": 0.41,
      "amn": 0.78,
      "thul": 0.49,
      "tal": 0.78,
      "ral": 0.11,
      "hel": 0.11
    },
    "items": {}
  },
  "craftedItemCount": 0,
  "transferredInCount": 0
}