{
  "address": "0xc1BF6F4171fCc089982d18C800828f75cf617f7a",
  "inventoryItemCount": 0,
  "equippedItemCount": 0,
  "marketTradeListedCount": 0,
  "marketTradeSoldCount": 0,
  "transferredOutCount": 0,
  "holdings": {},
  "points": 0,
  "guildId": 5,
  "joinedGuildAt": 1630293368661,
  "isGuildMembershipActive": false,
  "guildMembershipTokenId": null,
  "rewardHistory": [],
  "rewards": {
    "runes": {},
    "items": {}
  },
  "lifetimeRewards": {
    "runes": {},
    "items": {}
  },
  "craftedItemCount": 0,
  "transferredInCount": 0
}