{
  "address": "0x924b8c8B743857Cd6F085Cd3e86F4803F31EA2bb",
  "lastGamePlayed": 0,
  "inventoryItemCount": 0,
  "equippedItemCount": 0,
  "marketTradeListedCount": 0,
  "marketTradeSoldCount": 0,
  "transferredOutCount": 0,
  "holdings": {},
  "points": 55,
  "guildId": 5,
  "joinedGuildAt": 1630684805695,
  "isGuildMembershipActive": false,
  "guildMembershipTokenId": null,
  "rewardHistory": [
    {
      "id": "uEf9WgK_F",
      "rune": "tir",
      "value": 0.26,
      "timestamp": 1650126278748
    },
    {
      "id": "uEf9WgK_F",
      "rune": "ort",
      "value": 0.6499999999999999,
      "timestamp": 1650126278748
    },
    {
      "id": "uEf9WgK_F",
      "rune": "shael",
      "value": 0.52,
      "timestamp": 1650126278748
    },
    {
      "id": "uEf9WgK_F",
      "rune": "zod",
      "value": 0.5730000000000001,
      "timestamp": 1650126278748
    },
    {
      "id": "uEf9WgK_F",
      "rune": "tal",
      "value": 0.8,
      "timestamp": 1650126278748
    },
    {
      "id": "uEf9WgK_F",
      "rune": "dol",
      "value": 0.55,
      "timestamp": 1650126278748
    },
    {
      "id": "uEf9WgK_F",
      "rune": "ith",
      "value": 0.52,
      "timestamp": 1650126278748
    },
    {
      "id": "uEf9WgK_F",
      "rune": "nef",
      "value": 0.54,
      "timestamp": 1650126278748
    },
    {
      "id": "uEf9WgK_F",
      "rune": "thul",
      "value": 0.51,
      "timestamp": 1650126278748
    },
    {
      "id": "uEf9WgK_F",
      "rune": "amn",
      "value": 0.42,
      "timestamp": 1650126278748
    },
    {
      "id": "uEf9WgK_F",
      "rune": "sol",
      "value": 0.26,
      "timestamp": 1650126278748
    }
  ],
  "rewards": {
    "runes": {
      "tir": 0,
      "ort": 0,
      "shael": 0,
      "zod": 0,
      "tal": 0,
      "dol": 0,
      "ith": 0,
      "nef": 0,
      "thul": 0,
      "amn": 0,
      "sol": 0
    },
    "items": {}
  },
  "lifetimeRewards": {
    "runes": {
      "thul": 0.51,
      "tir": 0.26,
      "ort": 0.6499999999999999,
      "shael": 0.52,
      "zod": 0.5730000000000001,
      "tal": 0.8,
      "dol": 0.55,
      "ith": 0.52,
      "nef": 0.54,
      "amn": 0.42,
      "sol": 0.26
    },
    "items": {}
  },
  "craftedItemCount": 0,
  "transferredInCount": 0,
  "claimRequests": [
    {
      "id": "uEf9WgK_F",
      "timestamp": 1650126278748,
      "status": "processing"
    }
  ]
}