{
  "address": "0x0e4506d640E166dd3f8Cfd6039aD12fBa83Ae64d",
  "inventoryItemCount": 0,
  "equippedItemCount": 0,
  "marketTradeListedCount": 0,
  "marketTradeSoldCount": 0,
  "transferredOutCount": 0,
  "holdings": {},
  "points": 5,
  "guildId": 5,
  "joinedGuildAt": 1631652269208,
  "isGuildMembershipActive": false,
  "guildMembershipTokenId": null,
  "rewardHistory": [],
  "rewards": {
    "runes": {
      "zod": 0.017
    },
    "items": {}
  },
  "lifetimeRewards": {
    "runes": {
      "zod": 0.017
    },
    "items": {}
  },
  "craftedItemCount": 0,
  "transferredInCount": 0
}