{
  "hashes": [
    "eXBUlwa44"
  ],
  "servers": {
    "sa3": {
      "winStreak": 0,
      "kills": 8,
      "deaths": 88,
      "powerups": 3181,
      "evolves": 311,
      "points": 3638,
      "rewards": 6,
      "orbs": 1,
      "revenges": 0,
      "wins": 0,
      "rounds": 11,
      "winRatio": 0,
      "killDeathRatio": 0.09090909090909091,
      "roundPointRatio": 330.72727272727275,
      "averageLatency": 190.125,
      "timeSpent": 0.9,
      "hashHistory": {
        "R4ACzUBW0": 1,
        "WyaD23row": 1,
        "1w4Yyiwdg": 1,
        "5ii4/jYYc": 1,
        "ojH/Eo1Kc": 1,
        "hB6zlN0II": 1,
        "1YK40z2JU": 1,
        "8wURxPJqY": 1,
        "5rcuwn7d4": 1
      },
      "hashHistory2": {
        "DSiWkQc8Y": 7,
        "EqbFT8uiM": 7,
        "I9shbOpIA": 2,
        "qsy1JeYzE": 4,
        "P6WVRa7U4": 6,
        "C4nBghA54": 8,
        "vqEGje1jE": 5,
        "35ocG77E4": 7,
        "rUf/nxKQ8": 5,
        "WyaD23row": 11,
        "4hDBIDObc": 6,
        "U2GR6mdWE": 5,
        "rM2oHZcvI": 1,
        "69UQtqEd0": 3,
        "VOWNtciPg": 2,
        "4XSmgYeao": 3,
        "DNzxetpME": 1,
        "eXBUlwa44": 0,
        "qpjb/FeUk": 1,
        "ZmdzsxK+U": 8,
        "/cZzdu5zY": 6,
        "h9N+TVWMk": 6,
        "UfP8eN6FY": 6,
        "liwRvdv3Y": 2,
        "cMpZyucEM": 7,
        "VfvCxGN2Y": 3,
        "OvlCZYJOk": 1,
        "8P0QGkKNg": 3,
        "DaedTa3iI": 4,
        "4LAlwTfN4": 4,
        "ZIxM/mwPo": 4,
        "j56nWuktA": 2,
        "eJx3ty9V8": 7,
        "qmJRnHZ2w": 1,
        "sVhExbdgY": 1,
        "NL9HV2UIM": 1,
        "ccEc662ek": 3,
        "ENhpuBLpw": 1,
        "QM7a7h7vQ": 3,
        "iz5/sni2Q": 2,
        "5rcuwn7d4": 9,
        "A1UpnVHE8": 1,
        "pX+sV711M": 1,
        "TWpwbcVFU": 2,
        "Zx91EVU0w": 1,
        "DUjFQRlm8": 1,
        "nhrQ7cBY8": 2,
        "ojH/Eo1Kc": 7,
        "fcxu+LRBY": 3,
        "R4ACzUBW0": 6,
        "5ii4/jYYc": 5,
        "q8lc0uc9U": 5,
        "OkIv2iGyE": 7,
        "LRGPHqJQc": 7,
        "WPuQr1mZM": 3,
        "pzQs4VzZk": 1,
        "lprQ+jWfY": 3,
        "hB6zlN0II": 4,
        "Bksevt1ko": 2,
        "loB/sor7U": 8,
        "2jBN0TAf8": 1,
        "1w4Yyiwdg": 2,
        "Ax1tkp5sk": 2,
        "CrEv9qh2c": 9,
        "B6VGVueqc": 1,
        "1YK40z2JU": 5,
        "I9RvXeIKU": 1,
        "6+6BwI45k": 2,
        "jCW2WMRMg": 5,
        "+XfiNPp9g": 4,
        "8wURxPJqY": 2,
        "W/jDa4XNs": 1,
        "oQGngBYKQ": 2,
        "wfqzXA29I": 1,
        "2l84t/Wbc": 1,
        "8gq94hpi8": 1,
        "bRscJ4DTU": 2,
        "MqPgIOBIo": 1,
        "OWGg9et9Q": 2,
        "8cOuda1sQ": 2,
        "9ujPFg3nI": 2,
        "OMFWgqxO0": 1,
        "PB6pu7IS8": 1,
        "uv3Z1dnuo": 2,
        "9KOBcEOZY": 2,
        "zNeFKnGYg": 2,
        "TtWkAVW9s": 2,
        "o9TcdRoBI": 1,
        "BDdmhZFX8": 2,
        "GGgL22uKk": 2,
        "CbqNccUMU": 1,
        "asGICx4HY": 1,
        "MrB1n/v+8": 1,
        "clHi3w4Oc": 1
      },
      "ranking": {
        "kills": {
          "position": 1013,
          "total": 1299
        },
        "deaths": {
          "position": 620,
          "total": 1375
        },
        "powerups": {
          "position": 744,
          "total": 1398
        },
        "evolves": {
          "position": 759,
          "total": 1393
        },
        "points": {
          "position": 782,
          "total": 1396
        },
        "rewards": {
          "position": 930,
          "total": 1270
        },
        "orbs": {
          "position": 800,
          "total": 857
        },
        "revenges": {
          "position": 0,
          "total": 808
        },
        "rounds": {
          "position": 700,
          "total": 1398
        },
        "wins": {
          "position": 0,
          "total": 312
        },
        "timeSpent": {
          "position": 700,
          "total": 1398
        },
        "winRatio": {
          "position": 0,
          "total": 303
        },
        "killDeathRatio": {
          "position": 1276,
          "total": 1299
        },
        "roundPointRatio": {
          "position": 718,
          "total": 952
        },
        "averageLatency": {
          "position": 656,
          "total": 952
        }
      }
    },
    "sa5": {
      "winStreak": 0,
      "kills": 1,
      "deaths": 61,
      "powerups": 1311,
      "evolves": 102,
      "points": 1025,
      "rewards": 5,
      "orbs": 0,
      "revenges": 0,
      "wins": 0,
      "rounds": 5,
      "winRatio": 0,
      "killDeathRatio": 0.01639344262295082,
      "roundPointRatio": 205,
      "averageLatency": 174,
      "timeSpent": 0.4,
      "hashHistory": {
        "9j3QhQG4A": 1
      },
      "hashHistory2": {
        "71Dr0qoHM": 4,
        "L22A74dhg": 6,
        "3qfhdUPd4": 6,
        "S84x+nXw0": 6,
        "FzuS15NeY": 2,
        "U0ODRm3zk": 3,
        "Lgjs0ni2M": 5,
        "9j3QhQG4A": 5,
        "yxb8NfJrA": 4,
        "uuk6HKgBM": 1,
        "ifwarjggM": 5,
        "1RQhQhSac": 6,
        "oGzFgZ8kg": 6,
        "DgtgcqcQ0": 5,
        "eXBUlwa44": 0,
        "yEFlK/Cr8": 4,
        "RM00cnydw": 6,
        "Lg0F7fbg0": 5,
        "EGC5R3HKY": 5,
        "z6O5c8RgM": 5,
        "GjtEvxjWM": 4,
        "6rXxLa6Us": 2,
        "uB21Zhmcc": 4,
        "jnEq/3U4Q": 2,
        "T7wWo/+ws": 1,
        "NV/Jvg9AI": 2,
        "NRAlipAg4": 3,
        "24AqQmWbI": 1,
        "SJMvo17MM": 2,
        "Rj4tknS5M": 1,
        "TeXmI/uPE": 2,
        "T2cmegkko": 1,
        "YKs8v2KjE": 1
      },
      "ranking": {
        "kills": {
          "position": 958,
          "total": 996
        },
        "deaths": {
          "position": 537,
          "total": 1033
        },
        "powerups": {
          "position": 716,
          "total": 1059
        },
        "evolves": {
          "position": 768,
          "total": 1052
        },
        "points": {
          "position": 796,
          "total": 1058
        },
        "rewards": {
          "position": 769,
          "total": 984
        },
        "orbs": {
          "position": 0,
          "total": 678
        },
        "revenges": {
          "position": 0,
          "total": 658
        },
        "rounds": {
          "position": 688,
          "total": 1059
        },
        "wins": {
          "position": 0,
          "total": 244
        },
        "timeSpent": {
          "position": 688,
          "total": 1059
        },
        "winRatio": {
          "position": 0,
          "total": 238
        },
        "killDeathRatio": {
          "position": 996,
          "total": 996
        },
        "roundPointRatio": {
          "position": 646,
          "total": 715
        },
        "averageLatency": {
          "position": 472,
          "total": 715
        }
      }
    }
  },
  "overall": {
    "winStreak": 0,
    "kills": 9,
    "deaths": 149,
    "powerups": 4492,
    "evolves": 413,
    "points": 4663,
    "rewards": 11,
    "orbs": 1,
    "revenges": 0,
    "rounds": 16,
    "wins": 0,
    "timeSpent": 1.3,
    "winRatio": 0,
    "killDeathRatio": 0.06040268456375839,
    "roundPointRatio": 291.4375,
    "averageLatency": 182.0625,
    "ranking": {
      "kills": {
        "position": 9365,
        "total": 10828
      },
      "deaths": {
        "position": 5915,
        "total": 11144
      },
      "powerups": {
        "position": 7424,
        "total": 11254
      },
      "evolves": {
        "position": 7602,
        "total": 11233
      },
      "points": {
        "position": 7694,
        "total": 11245
      },
      "rewards": {
        "position": 7811,
        "total": 10417
      },
      "orbs": {
        "position": 8046,
        "total": 8159
      },
      "revenges": {
        "position": 0,
        "total": 7904
      },
      "rounds": {
        "position": 7029,
        "total": 11254
      },
      "wins": {
        "position": 0,
        "total": 3178
      },
      "timeSpent": {
        "position": 7163,
        "total": 11254
      },
      "winRatio": {
        "position": 0,
        "total": 3147
      },
      "killDeathRatio": {
        "position": 10768,
        "total": 10828
      },
      "roundPointRatio": {
        "position": 7699,
        "total": 9308
      },
      "averageLatency": {
        "position": 6364,
        "total": 8893
      }
    }
  },
  "lastUpdated": 1632780854494
}