{
  "hashes": [
    "ZL6N+KJoo"
  ],
  "servers": {
    "na1": {
      "winStreak": 0,
      "kills": 79,
      "deaths": 168,
      "powerups": 6849,
      "evolves": 636,
      "points": 14187,
      "rewards": 5,
      "orbs": 7,
      "revenges": 1,
      "wins": 0,
      "rounds": 18,
      "winRatio": 0,
      "killDeathRatio": 0.47023809523809523,
      "roundPointRatio": 788.1666666666666,
      "averageLatency": 161.8846153846154,
      "timeSpent": 1.5,
      "hashHistory": {
        "GKYkvQb0Q": 2,
        "hDOwrP6XU": 2,
        "yW2QUdCz8": 2,
        "uksGx9yOY": 3,
        "EZRdGJ+oA": 1,
        "x8HRvmmYE": 1,
        "yk6pK6Z+w": 2,
        "WyaD23row": 1,
        "iC50tD3ys": 1,
        "JfFSZgs1E": 1,
        "NZDzsrMEI": 1,
        "K3h0MdYiQ": 1,
        "QzEAlHy/g": 1,
        "iRFZuMiXI": 1,
        "RsCS4BgNg": 2,
        "6o3mHtWPo": 1,
        "k2kHyKvC4": 2,
        "jGz6eXvTQ": 1,
        "OLXP4gy/I": 1,
        "VoHLXr4wU": 1,
        "lvEhGunP8": 1,
        "/i3L9oetk": 1,
        "kkt9nz7+8": 1,
        "/2jK6mOBU": 1,
        "sq+/CFnhg": 1,
        "X/WupkFHw": 1,
        "24s+kdOGU": 1,
        "vB5T0sqGc": 1,
        "ycJfnHL0w": 2,
        "tRba2ziI0": 2,
        "IUP/XROVo": 1,
        "rgauPnRso": 1,
        "tGoJ3j+fI": 2,
        "tWDOM6vaQ": 2,
        "gG2pZuqCg": 1,
        "W6uZuDvME": 1,
        "8SNc3z2qc": 1,
        "0mPsOUJ94": 1,
        "aYpNYA9uY": 1,
        "alfEgrbXQ": 1,
        "gwccAF0gM": 5,
        "cqf76+riA": 1,
        "gxpoCqWXc": 1,
        "6HfhpbOl8": 1,
        "hbGULjOf8": 2,
        "091ydMkCU": 2,
        "hY2hD9STc": 1,
        "80eyLw//8": 2,
        "G3e/cDLoY": 1,
        "DrS0FP+wk": 3,
        "44K0pPmQA": 1,
        "CjBldTpU8": 2,
        "VNsHTVJUo": 2,
        "gtefFIqCo": 1,
        "SC5bTygXw": 1,
        "i7v5/jkn0": 1
      },
      "hashHistory2": {
        "Ash2e+jq0": 2,
        "YJkhoqs9E": 7,
        "6Lg0+HmIM": 12,
        "x8HRvmmYE": 11,
        "hDOwrP6XU": 11,
        "ckjFeog2g": 7,
        "iRFZuMiXI": 3,
        "JG0BKcspc": 2,
        "091ydMkCU": 14,
        "4rcEGWVPQ": 7,
        "pF+5bgn4g": 20,
        "iC50tD3ys": 4,
        "K3h0MdYiQ": 5,
        "PmOUkhR3g": 7,
        "+reaXkU6g": 5,
        "pWTzUt6x4": 2,
        "CVsW1U3q0": 9,
        "IrtvoorsA": 10,
        "u2YsLlyDs": 1,
        "sQFYbKjgg": 3,
        "LX3yObWgs": 6,
        "RsCS4BgNg": 9,
        "c85O/BcWs": 9,
        "BBdJrwVR8": 1,
        "NZDzsrMEI": 8,
        "iLPfJdqxk": 1,
        "W6uZuDvME": 14,
        "JfFSZgs1E": 2,
        "F3fl+0Xxk": 5,
        "XMMDwaKSE": 2,
        "keJSyBTKk": 6,
        "N31J/DT08": 1,
        "GKYkvQb0Q": 5,
        "nt33xrioA": 7,
        "ZL6N+KJoo": 0,
        "lvEhGunP8": 6,
        "W10YyoKIc": 8,
        "npPZSs+KI": 6,
        "L22A74dhg": 3,
        "yk6pK6Z+w": 5,
        "WyaD23row": 3,
        "yW2QUdCz8": 1,
        "vKyKCiVew": 1,
        "QzEAlHy/g": 6,
        "k2kHyKvC4": 5,
        "bWAfsMNqc": 1,
        "m0PZyy9FY": 6,
        "9P1OILdDc": 2,
        "Sx4Dg7iUI": 1,
        "O4INabsg0": 1,
        "J1nHNrqeE": 5,
        "NOqj/+4Wg": 2,
        "uksGx9yOY": 3,
        "XzAVqXgGk": 4,
        "xkOi+yqJA": 2,
        "6o3mHtWPo": 4,
        "EZRdGJ+oA": 1,
        "jGz6eXvTQ": 5,
        "pnzH8LP4M": 1,
        "0DQ5hEB7s": 2,
        "o5dd8QmLw": 1,
        "iHwbPOVos": 3,
        "g8A7uwaR0": 2,
        "jJpkHOXvg": 3,
        "cQw+aMQXI": 2,
        "+6GcjDqAM": 3,
        "fv8irlf3w": 1,
        "krU9Fs8Lo": 1,
        "VoHLXr4wU": 8,
        "i/lHqGkXs": 5,
        "CDBkB5vSw": 2,
        "knNZUmBKQ": 4,
        "/BH9kffws": 8,
        "OLXP4gy/I": 2,
        "DpY98H9UA": 1,
        "4NIzQVfnI": 2,
        "7vdbzWbZ0": 2,
        "8dyGHh1wg": 2,
        "hs/Q1mKn8": 2,
        "hEbX47IRo": 2,
        "0ESc2+IJE": 2,
        "N26Xb8MmI": 1,
        "1DOkuyp2w": 1,
        "OcyCmj2CQ": 1,
        "n6wu9zC+E": 5,
        "Q7yAJs1TY": 1,
        "wz9M6aCKk": 1,
        "i2YgD/Vbc": 1,
        "fYSijeB5U": 1,
        "FzAIU7aV0": 1,
        "ZP0k+UI9E": 5,
        "NGIyYJ7Cw": 5,
        "rgauPnRso": 4,
        "/2jK6mOBU": 7,
        "X/WupkFHw": 7,
        "MW6jd8U/4": 13,
        "/i3L9oetk": 8,
        "mvAopnwtU": 4,
        "VNsHTVJUo": 12,
        "ThrHKLGgY": 2,
        "kkt9nz7+8": 2,
        "kr9d7I7z8": 8,
        "7GliffN9Y": 1,
        "BLP8xyzjM": 8,
        "RNto72nq0": 3,
        "MbEyo0hJQ": 3,
        "aYpNYA9uY": 10,
        "sq+/CFnhg": 4,
        "nbOcgT1xs": 3,
        "zzXvDYKlI": 5,
        "QncjSTnSo": 8,
        "WSfzkhGrg": 3,
        "NFqpgE8Jc": 2,
        "7Ef9g5H7M": 2,
        "tRba2ziI0": 6,
        "alfEgrbXQ": 8,
        "DQ0p0kFY0": 3,
        "x5KI24Yzs": 3,
        "DImKOVO0g": 3,
        "GIYy4Yvvg": 1,
        "mccRKWXlU": 1,
        "7cga9BSs4": 7,
        "dz2uCSOig": 8,
        "ubTMNXoRI": 1,
        "aUKYeMl1M": 1,
        "STnDsSEjg": 5,
        "YQSQnLR3M": 8,
        "44K0pPmQA": 9,
        "Tb8XUpBgc": 1,
        "24s+kdOGU": 8,
        "jPf0oi97U": 3,
        "F6eYvcwbc": 1,
        "ZZ+e3Ux74": 3,
        "1Oi6ufwW0": 6,
        "HNWaP+ius": 1,
        "vU7FZi/q0": 1,
        "Hrq4FKdzM": 3,
        "yY8H0LsEU": 3,
        "HphFq/lMM": 2,
        "oZIWyZa0c": 3,
        "zu9Y6l07U": 1,
        "xksRQGg3o": 7,
        "u9sTw6jqk": 5,
        "N7ai9Nmp4": 1,
        "c5iVO3GKE": 1,
        "gG2pZuqCg": 6,
        "DzXKfAO9g": 1,
        "e87/Aqn5A": 4,
        "8SNc3z2qc": 5,
        "J0dDdRx+0": 6,
        "ycJfnHL0w": 3,
        "cLKcZgQYk": 6,
        "sjDf4amOE": 1,
        "FXLMkQIYA": 6,
        "0QRzfRJZI": 6,
        "mfMtZlK7A": 6,
        "BxkogkRoo": 1,
        "Hszrv1Izo": 1,
        "khMjlqd0o": 1,
        "vLm83n/bw": 1,
        "RjP46mxro": 2,
        "ZPmcU5DFw": 1,
        "IUP/XROVo": 2,
        "2OItlYIsk": 5,
        "tWDOM6vaQ": 3,
        "0mPsOUJ94": 4,
        "F0ajEbb5I": 3,
        "B/UHadfuE": 1,
        "NBcS/zI4E": 1,
        "vB5T0sqGc": 0,
        "2cWHTDxOw": 4,
        "i6lNW+P70": 10,
        "trTJC68kY": 1,
        "bEik53oVo": 1,
        "8c7QtfS1M": 1,
        "WDcE3KJYY": 1,
        "zukynC/ko": 4,
        "T+cY36Sa0": 6,
        "tGoJ3j+fI": 2,
        "uezVySFww": 2,
        "thtpkDtwg": 1,
        "unrbCFbdg": 3,
        "6SyyMO/PA": 2,
        "uzBXDT0Pw": 2,
        "3WFHOnrUY": 3,
        "QBzz7hX6A": 1,
        "OWvzxly5o": 1,
        "wflYydMdg": 2,
        "0+zl1yfLQ": 2,
        "DPCEK9ouM": 2,
        "fkP6eU5/g": 2,
        "nrIO+UDyk": 1,
        "ngnTrp+7c": 2,
        "m1ENgxWqE": 2,
        "Tgjj+w514": 1,
        "pL1FtmS0Y": 1,
        "Zudu9Hwi4": 1,
        "MXEa62QeU": 2,
        "CJUY2+CuU": 2,
        "ffckTREb4": 4,
        "yI7RYIkS0": 1,
        "CnX10Z/48": 1,
        "Fsgdy+Is0": 1,
        "eo3ZUxJSM": 1,
        "dltypwS94": 1,
        "ZEvWMh+TA": 2,
        "0RPt6Ti9c": 5,
        "G3e/cDLoY": 4,
        "lUxEnx6Sg": 5,
        "1AcPrVu/E": 2,
        "UY2JM53LA": 3,
        "80eyLw//8": 4,
        "rv8dmc8bU": 5,
        "SC5bTygXw": 4,
        "LVCdl/ris": 2,
        "sS3QLQkOY": 5,
        "6HfhpbOl8": 4,
        "wyE7KUw94": 3,
        "OMIcntGBY": 3,
        "zedURpa+w": 1,
        "q8hFqPB7U": 5,
        "ukY/+9GBg": 3,
        "QooTX0IQw": 4,
        "cHVRq722w": 3,
        "iilVTRGS8": 1,
        "F8JL1mA8Q": 5,
        "VerC81H4s": 5,
        "CjBldTpU8": 4,
        "F7KkHHya0": 4,
        "xNgJ8jVHQ": 5,
        "IY6KqWAAA": 4,
        "LpJVkoaW4": 1,
        "Kh0jnlZGI": 2,
        "AsmBe3XYk": 1,
        "hbGULjOf8": 3,
        "96LJpEM/w": 1,
        "EUP81nBXE": 1,
        "3VCltinHg": 3,
        "QiJsoUd+Q": 2,
        "ezXXwmfQ8": 3,
        "gxpoCqWXc": 3,
        "cqf76+riA": 2,
        "jUj1MseKs": 1,
        "gwccAF0gM": 1,
        "ZH8mNGIJ4": 4,
        "3sFWNiP34": 1,
        "88J0mZm2g": 4,
        "nda8FiNA4": 1,
        "rV1WXlDOk": 1,
        "5V+u3glms": 4,
        "hY2hD9STc": 2,
        "RRAN3AQRM": 2,
        "WDnEygtyc": 3,
        "gyDubDXLo": 3,
        "CdCZmlBd4": 1,
        "gFFqP3ADU": 3,
        "NdwgKkqIg": 3,
        "54Hsh3QVc": 1,
        "62wlpXGKU": 3,
        "Fq5TOVLFU": 1,
        "QMOiarTlw": 2,
        "h9A2QjDX0": 2,
        "gtefFIqCo": 1,
        "dOsUegRK0": 1,
        "DrS0FP+wk": 1,
        "m8V4UUgDc": 1,
        "ArG6zsThc": 1,
        "ne3Dn0CYE": 2,
        "i7v5/jkn0": 0,
        "XD+MPYtHA": 1,
        "eSlDviu3g": 1,
        "8iLP9GvGs": 1,
        "Y4z9C4yMs": 1
      },
      "ranking": {
        "kills": {
          "position": 1014,
          "total": 2771
        },
        "deaths": {
          "position": 856,
          "total": 2951
        },
        "powerups": {
          "position": 1130,
          "total": 2999
        },
        "evolves": {
          "position": 1193,
          "total": 2995
        },
        "points": {
          "position": 991,
          "total": 2996
        },
        "rewards": {
          "position": 1773,
          "total": 2502
        },
        "orbs": {
          "position": 884,
          "total": 1706
        },
        "revenges": {
          "position": 1466,
          "total": 1616
        },
        "rounds": {
          "position": 1104,
          "total": 2999
        },
        "wins": {
          "position": 0,
          "total": 548
        },
        "timeSpent": {
          "position": 1104,
          "total": 2999
        },
        "winRatio": {
          "position": 0,
          "total": 533
        },
        "killDeathRatio": {
          "position": 2124,
          "total": 2771
        },
        "roundPointRatio": {
          "position": 687,
          "total": 1853
        },
        "averageLatency": {
          "position": 1245,
          "total": 1853
        }
      }
    }
  },
  "overall": {
    "winStreak": 0,
    "kills": 79,
    "deaths": 168,
    "powerups": 6849,
    "evolves": 636,
    "points": 14187,
    "rewards": 5,
    "orbs": 7,
    "revenges": 1,
    "rounds": 18,
    "wins": 0,
    "timeSpent": 1.5,
    "winRatio": 0,
    "killDeathRatio": 0.47023809523809523,
    "roundPointRatio": 788.1666666666666,
    "averageLatency": 161.8846153846154,
    "ranking": {
      "kills": {
        "position": 5899,
        "total": 10828
      },
      "deaths": {
        "position": 5596,
        "total": 11144
      },
      "powerups": {
        "position": 6545,
        "total": 11254
      },
      "evolves": {
        "position": 6746,
        "total": 11233
      },
      "points": {
        "position": 5708,
        "total": 11245
      },
      "rewards": {
        "position": 8878,
        "total": 10417
      },
      "orbs": {
        "position": 5042,
        "total": 8159
      },
      "revenges": {
        "position": 7331,
        "total": 7904
      },
      "rounds": {
        "position": 6697,
        "total": 11254
      },
      "wins": {
        "position": 0,
        "total": 3178
      },
      "timeSpent": {
        "position": 6737,
        "total": 11254
      },
      "winRatio": {
        "position": 0,
        "total": 3147
      },
      "killDeathRatio": {
        "position": 7378,
        "total": 10828
      },
      "roundPointRatio": {
        "position": 3275,
        "total": 9308
      },
      "averageLatency": {
        "position": 5621,
        "total": 8893
      }
    }
  },
  "lastUpdated": 1631437843734
}